LICENSE.txt
README.md
setup.cfg
setup.py
os_image_handler/image_handler.py
os_image_handler.egg-info/PKG-INFO
os_image_handler.egg-info/SOURCES.txt
os_image_handler.egg-info/dependency_links.txt
os_image_handler.egg-info/requires.txt
os_image_handler.egg-info/top_level.txt