Metadata-Version: 2.1
Name: os-image-handler
Version: 1.15
Summary: This script contains fundamental image manipulation actions.
Home-page: https://github.com/osfunapps/os-image-handler-py
Author: Oz Shabat
Author-email: admin@os-apps.com
License: MIT
Keywords: python,osfunapps,osapps,image,image manipulation
Classifier: Development Status :: 5 - Production/Stable
Classifier: Intended Audience :: Developers
Classifier: Topic :: Software Development :: Build Tools
Classifier: License :: OSI Approved :: MIT License
Classifier: Programming Language :: Python :: 3
Classifier: Programming Language :: Python :: 3.4
Classifier: Programming Language :: Python :: 3.5
Classifier: Programming Language :: Python :: 3.6
Classifier: Programming Language :: Python :: 3.9
License-File: LICENSE.txt
